migrate3.py
migrate3-0.3.11.dist-info/DESCRIPTION.rst
migrate3-0.3.11.dist-info/entry_points.txt
migrate3-0.3.11.dist-info/METADATA
migrate3-0.3.11.dist-info/metadata.json
migrate3-0.3.11.dist-info/RECORD
migrate3-0.3.11.dist-info/top_level.txt
migrate3-0.3.11.dist-info/WHEEL
